LICENCE
README.md
setup.cfg
setup.py
checklib/__init__.py
checklib/assertions.py
checklib/checker.py
checklib/generators.py
checklib/http.py
checklib/internal.py
checklib/requirements.py
checklib/status.py
checklib/utils.py
checklib.egg-info/PKG-INFO
checklib.egg-info/SOURCES.txt
checklib.egg-info/dependency_links.txt
checklib.egg-info/requires.txt
checklib.egg-info/top_level.txt
checklib/resources/useragents.txt
checklib/resources/usernames.txt