Metadata-Version: 2.1
Name: checklib
Version: 0.6.0
Summary: Library for convenient checker writing
Home-page: https://github.com/pomo-mondreganto/
Download-URL: https://github.com/pomo-mondreganto/checklib/archive/v_0.6.0.tar.gz
Author: Roman Nikitin
Author-email: nikrom.prog@gmail.com
License: MIT
Keywords: AD,CTF,checker
Classifier: Development Status :: 3 - Alpha
Classifier: Topic :: Software Development :: Build Tools
Classifier: License :: OSI Approved :: MIT License
Classifier: Programming Language :: Python :: 3.8
Classifier: Programming Language :: Python :: 3.9
Classifier: Programming Language :: Python :: 3.10
Classifier: Programming Language :: Python :: 3.11
License-File: LICENCE
